[
    {
        "judul": "BMKG Prediksi Hujan Lebat Masih Terjadi Sepekan ke Depan di Jabar",
        "kategori": "News",
        "publish_time": "19 detik yang lalu",
        "scraping_time": "2024-04-15 12:55:55"
    },
    {
        "judul": "Pinjaman BRI Dorong Oleh-oleh Keripik Tempe Sukses Kembangkan Usaha",
        "kategori": "Ekonomi",
        "publish_time": "3 menit yang lalu",
        "scraping_time": "2024-04-15 12:55:55"
    },
    {
        "judul": "Jasa Marga: 961 Ribu Kendaraan Sudah Kembali ke Jabotabek pada H+3 Lebaran",
        "kategori": "News",
        "publish_time": "4 menit yang lalu",
        "scraping_time": "2024-04-15 12:55:55"
    },
    {
        "judul": "Leverkusen Juara, Granit Xhaka Rasakan Momen Paling Spesial Dalam 14 Tahun Kariernya",
        "kategori": "Kabar Ramadhan",
        "publish_time": "Senin , 15 Apr 2024, 12:29 WIB",
        "scraping_time": "2024-04-15 12:55:55"
    },
    {
        "judul": "Bagaimana Israel Menghalau Ratusan Rudal Iran?",
        "kategori": "Kabar Ramadhan",
        "publish_time": "Senin , 15 Apr 2024, 12:25 WIB",
        "scraping_time": "2024-04-15 12:55:55"
    },
    {
        "judul": "Menkeu Rapat dengan Jajaran Eselon I Bahas Tensi Geopolitik Terkini",
        "kategori": "Kabar Ramadhan",
        "publish_time": "Senin , 15 Apr 2024, 11:25 WIB",
        "scraping_time": "2024-04-15 12:55:55"
    },
    {
        "judul": "Buya Anwar: Dunia Harusnya Mendukung Iran",
        "kategori": "Kabar Ramadhan",
        "publish_time": "Senin , 15 Apr 2024, 10:50 WIB",
        "scraping_time": "2024-04-15 12:55:55"
    },
    {
        "judul": "Pemprov Jatim Buka 5.200 Formasi pada Rekrutmen CASN 2024",
        "kategori": "Kabar Ramadhan",
        "publish_time": "Senin , 15 Apr 2024, 10:35 WIB",
        "scraping_time": "2024-04-15 12:55:55"
    },
    {
        "judul": "Penampillan Buruk Babak Kedua Jadi Alasan Arsenal Dipermakukan Aston Villa di Emirates",
        "kategori": "Sport",
        "publish_time": "5 menit yang lalu",
        "scraping_time": "2024-04-15 12:55:55"
    },
    {
        "judul": "BRI Sediakan Posko Mudik di Delapan Titik Strategis",
        "kategori": "Tekno",
        "publish_time": "6 menit yang lalu",
        "scraping_time": "2024-04-15 12:55:55"
    },
    {
        "judul": "Antisipasi Puncak\u00a0Arus Balik, Jumlah Kapal Rute Pelabuhan Panjang-Ciwandan Ditambah",
        "kategori": "Kabar Pemilu",
        "publish_time": "Kamis , 11 Apr 2024, 14:14 WIB",
        "scraping_time": "2024-04-15 12:55:55"
    },
    {
        "judul": "Permintaan Masih Tinggi,\u00a0Pertamina Tambah 14,4 Juta Tabung LPG 3 Kg",
        "kategori": "Prabowo Gibran",
        "publish_time": "Rabu , 10 Apr 2024, 19:19 WIB",
        "scraping_time": "2024-04-15 12:55:55"
    },
    {
        "judul": "PBNU: Serangan Iran Mewakili Kemarahan Dunia Terhadap Israel",
        "kategori": "Anies Muhaimin",
        "publish_time": "Rabu , 10 Apr 2024, 18:55 WIB",
        "scraping_time": "2024-04-15 12:55:55"
    },
    {
        "judul": "Perkuat Program Pompanisasi, Kementan Dorong Listrik Masuk Sawah",
        "kategori": "Prabowo Gibran",
        "publish_time": "Rabu , 10 Apr 2024, 18:28 WIB",
        "scraping_time": "2024-04-15 12:55:55"
    },
    {
        "judul": "TNI-Polri Minta Maaf Atas Insiden Bentrok di Sorong",
        "kategori": "Prabowo Gibran",
        "publish_time": "Rabu , 10 Apr 2024, 18:09 WIB",
        "scraping_time": "2024-04-15 12:55:55"
    },
    {
        "judul": "Garuda Indonesia Monitor Situasi Timur Tengah Pascaserangan Iran ke Israel",
        "kategori": "Ekonomi",
        "publish_time": "8 menit yang lalu",
        "scraping_time": "2024-04-15 12:55:55"
    },
    {
        "judul": "Waketum MUI: Serangan Iran Ingatkan Israel Agar tidak Berlaku Sombong",
        "kategori": "Close Up",
        "publish_time": "Senin , 15 Apr 2024, 11:57 WIB",
        "scraping_time": "2024-04-15 12:55:55"
    },
    {
        "judul": "Mengenal Robot Kecil yang Bisa Melompat dalam Gravitasi Nol untuk Menjelajahi Asteroid",
        "kategori": "Close Up",
        "publish_time": "Senin , 15 Apr 2024, 10:14 WIB",
        "scraping_time": "2024-04-15 12:55:55"
    },
    {
        "judul": "Dibayangi Perang, Harga Emas Antam Naik Tipis Jadi Rp 1,315 Juta per Gram",
        "kategori": "Info37",
        "publish_time": "Senin , 15 Apr 2024, 09:13 WIB",
        "scraping_time": "2024-04-15 12:55:55"
    },
    {
        "judul": "Tim SAR Gabungan Lanjutkan Pencarian Korban Longsor di Tana Toraja",
        "kategori": "Close Up",
        "publish_time": "Senin , 15 Apr 2024, 08:07 WIB",
        "scraping_time": "2024-04-15 12:55:55"
    },
    {
        "judul": "Kawal Arus Balik Lebaran, PLN Siaga di 10 Titik Krusial Transportasi Publik di Jakarta",
        "kategori": "Close Up",
        "publish_time": "Ahad , 14 Apr 2024, 22:01 WIB",
        "scraping_time": "2024-04-15 12:55:55"
    },
    {
        "judul": "Puncak Arus Balik, KAI Layani 218 Ribu Penumpang Pada Ahad",
        "kategori": "Khazanah",
        "publish_time": "10 menit yang lalu",
        "scraping_time": "2024-04-15 12:55:55"
    },
    {
        "judul": "Ini Spesifikasi Drone 'Kamikaze' yang Digunakan Iran dalam Serangan ke Israel",
        "kategori": "Happening",
        "publish_time": "Senin , 15 Apr 2024, 12:09 WIB",
        "scraping_time": "2024-04-15 12:55:55"
    },
    {
        "judul": "Setelah Jadi Juara Asia, Jonatan Christie Sampaikan Dukungan untuk Timnas Indonesia U-23",
        "kategori": "Family",
        "publish_time": "Senin , 15 Apr 2024, 12:05 WIB",
        "scraping_time": "2024-04-15 12:55:55"
    },
    {
        "judul": "Sebanyak 13 RT Masih Tergenang Akibat Hujan Kemarin",
        "kategori": "Happening",
        "publish_time": "Senin , 15 Apr 2024, 11:16 WIB",
        "scraping_time": "2024-04-15 12:55:55"
    },
    {
        "judul": "DIY Bakal Diguyur Hujan Lebat Disertai Angin Kencang Siang Hingga Sore Ini",
        "kategori": "Happening",
        "publish_time": "Senin , 15 Apr 2024, 10:16 WIB",
        "scraping_time": "2024-04-15 12:55:55"
    },
    {
        "judul": "Ketum PSSI: Bismillah, Kita Dukung dan Doakan Perjuangan Garuda Muda di Asia",
        "kategori": "Happening",
        "publish_time": "Senin , 15 Apr 2024, 09:11 WIB",
        "scraping_time": "2024-04-15 12:55:55"
    },
    {
        "judul": "Ilmuwan Ungkap Tabrakan Kosmis Dahsyat yang Membentuk Nebula Telur Naga",
        "kategori": "News",
        "publish_time": "11 menit yang lalu",
        "scraping_time": "2024-04-15 12:55:55"
    },
    {
        "judul": "Arus Balik, Tiket KA di Daop 6 Yogyakarta Masih Tersedia Hingga 21 April",
        "kategori": "Sport",
        "publish_time": "11 menit yang lalu",
        "scraping_time": "2024-04-15 12:55:55"
    },
    {
        "judul": "Meski Hiatus, Anggota BTS Tetap Cuan Karena Ini",
        "kategori": "Ekonomi",
        "publish_time": "13 menit yang lalu",
        "scraping_time": "2024-04-15 12:55:55"
    },
    {
        "judul": "Balita Pukuli Diri Sendiri Saat Tantrum, Bagaimana Cara Mengatasinya?",
        "kategori": "Lingkungan",
        "publish_time": "Ahad , 14 Apr 2024, 09:29 WIB",
        "scraping_time": "2024-04-15 12:55:55"
    },
    {
        "judul": "Pengamat Nilai Peluang Timnas Indonesia U-23 Sama Kuat, Qatar Bukan Tim Istimewa",
        "kategori": "Tata Kelola",
        "publish_time": "Ahad , 14 Apr 2024, 03:10 WIB",
        "scraping_time": "2024-04-15 12:55:55"
    },
    {
        "judul": "Tol Japek Arah Jakarta Dipadati Kendaraan Arus Balik Pemudik",
        "kategori": "Tata Kelola",
        "publish_time": "Sabtu , 13 Apr 2024, 14:30 WIB",
        "scraping_time": "2024-04-15 12:55:55"
    },
    {
        "judul": "KAI Commuter Wilayah 8 Surabaya Layani Ratusan Ribu Penumpang Selama Libur Lebaran",
        "kategori": "Tata Kelola",
        "publish_time": "Sabtu , 13 Apr 2024, 14:15 WIB",
        "scraping_time": "2024-04-15 12:55:55"
    },
    {
        "judul": "Reaksi Internasional Terhadap Serangan Iran ke Israel",
        "kategori": "Tata Kelola",
        "publish_time": "Sabtu , 13 Apr 2024, 13:45 WIB",
        "scraping_time": "2024-04-15 12:55:55"
    },
    {
        "judul": "Usai Ramadhan, Jusuf Kalla Ajak Umat Islam Tetap Ramaikan Masjid",
        "kategori": "Ramadhan",
        "publish_time": "15 menit yang lalu",
        "scraping_time": "2024-04-15 12:55:55"
    },
    {
        "judul": "Shin Tae-yong Sebut Persaingan Grup A Piala Asia U-23 Sangat Kompetitif",
        "kategori": "Ekonomi",
        "publish_time": "18 menit yang lalu",
        "scraping_time": "2024-04-15 12:55:55"
    },
    {
        "judul": "Prakiraan Cuaca DIY Hari Ini: Hujan Sedang-Lebat, Ada Potensi Angin Kencang",
        "kategori": "Khazanah",
        "publish_time": "18 menit yang lalu",
        "scraping_time": "2024-04-15 12:55:55"
    },
    {
        "judul": "BPBD DKI: 18 RT di Jaktim Banjir Akibat Luapan Kali Ciliwung",
        "kategori": "Ekonomi",
        "publish_time": "19 menit yang lalu",
        "scraping_time": "2024-04-15 12:55:55"
    },
    {
        "judul": "Ini Prediksi Starting XI Timnas Indonesia U-23 Vs Qatar pada Laga Pembuka Piala Asia U-23",
        "kategori": "Finansial",
        "publish_time": "Senin , 15 Apr 2024, 12:53 WIB",
        "scraping_time": "2024-04-15 12:55:55"
    },
    {
        "judul": "Wisatawan Pilih Berkemah di Puncak Bogor Habiskan Libur Lebaran",
        "kategori": "Finansial",
        "publish_time": "Senin , 15 Apr 2024, 12:48 WIB",
        "scraping_time": "2024-04-15 12:55:55"
    },
    {
        "judul": "Netanyahu Putuskan Tunda Serangan Militer di Rafah",
        "kategori": "Finansial",
        "publish_time": "Senin , 15 Apr 2024, 12:42 WIB",
        "scraping_time": "2024-04-15 12:55:55"
    },
    {
        "judul": "Tampil di Coachella, Le Sserafim Kejutkan Penggemar dengan Lagu Baru",
        "kategori": "Energi",
        "publish_time": "Senin , 15 Apr 2024, 12:38 WIB",
        "scraping_time": "2024-04-15 12:55:55"
    },
    {
        "judul": "Kemungkinan Gabungnya PDIP ke Koalisi, Idrus Marham: Ada Hitung-Hitungannya",
        "kategori": "Pertanian",
        "publish_time": "Senin , 15 Apr 2024, 12:36 WIB",
        "scraping_time": "2024-04-15 12:55:55"
    },
    {
        "judul": "Puncak Arus Balik di Jalur Nagreg Terjadi Ahad Lalu, Ada 143.800 Kendaraan",
        "kategori": "News",
        "publish_time": "21 menit yang lalu",
        "scraping_time": "2024-04-15 12:55:55"
    },
    {
        "judul": "Apa yang Terjadi dalam Gelombang Serangan Iran dan Mengapa Drone Mereka Ditakuti?",
        "kategori": "Ekonomi",
        "publish_time": "22 menit yang lalu",
        "scraping_time": "2024-04-15 12:55:55"
    },
    {
        "judul": "Pemda DIY Gelar Griya Lebaran 16 April 2024, Masyarakat Dipersilakan Datang",
        "kategori": "Khazanah",
        "publish_time": "22 menit yang lalu",
        "scraping_time": "2024-04-15 12:55:55"
    },
    {
        "judul": "Biaya Kuliah IPB Jalur SNBP, SNBT, dan Mandiri 2024, UKT Terendah Rp 500 Ribu",
        "kategori": "Tekno",
        "publish_time": "24 menit yang lalu",
        "scraping_time": "2024-04-15 12:55:55"
    },
    {
        "judul": "Alat AI Inovatif Baru Janjikan Revolusi Cara Interpretasi Gambar-Gambar Medis",
        "kategori": "Ekonomi",
        "publish_time": "25 menit yang lalu",
        "scraping_time": "2024-04-15 12:55:55"
    },
    {
        "judul": "Polda Lampung Klaim Penanganan Puncak Arus Balik di Bakauheni Terkendali",
        "kategori": "Visual",
        "publish_time": "26 menit yang lalu",
        "scraping_time": "2024-04-15 12:55:55"
    }
]